{
  "url": "https://allianceforcoffeeexcellence.org/brazil-pulped-naturals-2003/",
  "scraped_month": "2026-06",
  "lots": [
    {
      "AuctionSlug": "brazil-pulped-naturals-2003",
      "AuctionYear": 2003,
      "Country": "Brazil",
      "LotRank": "1",
      "LotType": "COE",
      "FarmName": "Fazenda Serra do Bon\u00e9",
      "ProducerName": "Carlos S\u00e9rgio Sanglard",
      "Region": "Araponga, MG",
      "Process": "Pulped Natural",
      "Varietal": "",
      "WeightKg": null,
      "ScoreCoE": 95.35,
      "PriceUSDPerLb": 10.15,
      "TotalValueUSD": 52361.99,
      "BuyerName": "Maruyama Coffee ( Mikatajuku group)",
      "ScrapedMonth": "2026-06"
    },
    {
      "AuctionSlug": "brazil-pulped-naturals-2003",
      "AuctionYear": 2003,
      "Country": "Brazil",
      "LotRank": "2",
      "LotType": "COE",
      "FarmName": "Fazenda Esperan\u00e7a",
      "ProducerName": "C\u00edcero Viegas Cavalcanti De Albuquerque",
      "Region": "Carmo De Minas, Sul de Minas",
      "Process": "Pulped Natural",
      "Varietal": "",
      "WeightKg": null,
      "ScoreCoE": 93.72,
      "PriceUSDPerLb": 7.1,
      "TotalValueUSD": 18783.38,
      "BuyerName": "Mercanta The Coffee Hunters for Monmouth Coffee Company, Cafes Meo, Cafes El Magnifico Barcelona and The Coffee Company",
      "ScrapedMonth": "2026-06"
    },
    {
      "AuctionSlug": "brazil-pulped-naturals-2003",
      "AuctionYear": 2003,
      "Country": "Brazil",
      "LotRank": "3",
      "LotType": "COE",
      "FarmName": "Fazenda do Serrado",
      "ProducerName": "Maria Rog\u00e9ria Costa Pereira",
      "Region": "Carmo de Minas, Minas Gerais",
      "Process": "Pulped Natural",
      "Varietal": "",
      "WeightKg": null,
      "ScoreCoE": 91.8,
      "PriceUSDPerLb": 6.03,
      "TotalValueUSD": 16750.28,
      "BuyerName": "Bontain Coffee co.,ltd.",
      "ScrapedMonth": "2026-06"
    },
    {
      "AuctionSlug": "brazil-pulped-naturals-2003",
      "AuctionYear": 2003,
      "Country": "Brazil",
      "LotRank": "4",
      "LotType": "COE",
      "FarmName": "Fazenda Recreio",
      "ProducerName": "Joaquim Jos\u00e9 de Carvalho Dias",
      "Region": "S\u00e3o Sebasti\u00e3o da Grama, SP",
      "Process": "Pulped Natural",
      "Varietal": "",
      "WeightKg": null,
      "ScoreCoE": 90.93,
      "PriceUSDPerLb": 5.15,
      "TotalValueUSD": 13624.57,
      "BuyerName": "SAN ANTONIO COFFEE ROASTERS",
      "ScrapedMonth": "2026-06"
    },
    {
      "AuctionSlug": "brazil-pulped-naturals-2003",
      "AuctionYear": 2003,
      "Country": "Brazil",
      "LotRank": "5",
      "LotType": "COE",
      "FarmName": "Fazenda Serra das Cabe\u00e7as",
      "ProducerName": "Paulo Augusto Caram Nascif",
      "Region": "Araponga, Minas Gerais",
      "Process": "Pulped Natural",
      "Varietal": "",
      "WeightKg": null,
      "ScoreCoE": 90.91,
      "PriceUSDPerLb": 4.05,
      "TotalValueUSD": 18214.59,
      "BuyerName": "TOA COFFEE Co.,Ltd.",
      "ScrapedMonth": "2026-06"
    },
    {
      "AuctionSlug": "brazil-pulped-naturals-2003",
      "AuctionYear": 2003,
      "Country": "Brazil",
      "LotRank": "6",
      "LotType": "COE",
      "FarmName": "Fazenda S\u00e3o Francisco",
      "ProducerName": "In\u00eas Zoli Tassinari",
      "Region": "S\u00e3o Jos\u00e9 Vale Rio Preto, Rio de Janeiro",
      "Process": "Pulped Natural",
      "Varietal": "",
      "WeightKg": null,
      "ScoreCoE": 90.78,
      "PriceUSDPerLb": 5.1,
      "TotalValueUSD": 13492.29,
      "BuyerName": "Solberg & Hansen AS",
      "ScrapedMonth": "2026-06"
    },
    {
      "AuctionSlug": "brazil-pulped-naturals-2003",
      "AuctionYear": 2003,
      "Country": "Brazil",
      "LotRank": "7",
      "LotType": "COE",
      "FarmName": "Fazenda S\u00e3o Paulo",
      "ProducerName": "Paulo Moreira de Paiva",
      "Region": "S\u00e3o Sebasti\u00e3o da Grama, S\u00e3o Paulo",
      "Process": "Pulped Natural",
      "Varietal": "",
      "WeightKg": null,
      "ScoreCoE": 90.7,
      "PriceUSDPerLb": 5.6,
      "TotalValueUSD": 45185.95,
      "BuyerName": "Diedrich Coffee, Inc.",
      "ScrapedMonth": "2026-06"
    },
    {
      "AuctionSlug": "brazil-pulped-naturals-2003",
      "AuctionYear": 2003,
      "Country": "Brazil",
      "LotRank": "8",
      "LotType": "COE",
      "FarmName": "S\u00edtio Lenice",
      "ProducerName": "Milton Faria Bonette",
      "Region": "Pedralva, Minas Gerais",
      "Process": "Pulped Natural",
      "Varietal": "",
      "WeightKg": null,
      "ScoreCoE": 90.41,
      "PriceUSDPerLb": 3.56,
      "TotalValueUSD": 11301.78,
      "BuyerName": "WATARU for TOHO COFFEE",
      "ScrapedMonth": "2026-06"
    },
    {
      "AuctionSlug": "brazil-pulped-naturals-2003",
      "AuctionYear": 2003,
      "Country": "Brazil",
      "LotRank": "9",
      "LotType": "COE",
      "FarmName": "Fazenda Santa Mariana",
      "ProducerName": "Sebasti\u00e3o Marcio de Carvalho Junqueira",
      "Region": "Dom Vi\u00e7oso, MG",
      "Process": "Pulped Natural",
      "Varietal": "",
      "WeightKg": null,
      "ScoreCoE": 89.2,
      "PriceUSDPerLb": 2.6,
      "TotalValueUSD": 14444.69,
      "BuyerName": "Caravan Coffee Co.,Ltd.",
      "ScrapedMonth": "2026-06"
    },
    {
      "AuctionSlug": "brazil-pulped-naturals-2003",
      "AuctionYear": 2003,
      "Country": "Brazil",
      "LotRank": "10",
      "LotType": "COE",
      "FarmName": "Fazenda Santa in\u00eas",
      "ProducerName": "Luiz Botelho de Macedo Costa (Esp\u00f3lio)",
      "Region": "S\u00e3o Sebasti\u00e3o da Grama, State of S\u00e3o Paulo",
      "Process": "Pulped Natural",
      "Varietal": "",
      "WeightKg": null,
      "ScoreCoE": 89.1,
      "PriceUSDPerLb": 3.55,
      "TotalValueUSD": 9391.69,
      "BuyerName": "Arab Coffee Co., Ltd",
      "ScrapedMonth": "2026-06"
    },
    {
      "AuctionSlug": "brazil-pulped-naturals-2003",
      "AuctionYear": 2003,
      "Country": "Brazil",
      "LotRank": "11",
      "LotType": "COE",
      "FarmName": "Fazenda Apucarana",
      "ProducerName": "Am\u00e9lia Ferracioli Delarisse",
      "Region": "Patroc\u00ednio, Minas Gerais",
      "Process": "Pulped Natural",
      "Varietal": "",
      "WeightKg": null,
      "ScoreCoE": 87.11,
      "PriceUSDPerLb": 4.0,
      "TotalValueUSD": 10053.08,
      "BuyerName": "The Roasterie Inc",
      "ScrapedMonth": "2026-06"
    },
    {
      "AuctionSlug": "brazil-pulped-naturals-2003",
      "AuctionYear": 2003,
      "Country": "Brazil",
      "LotRank": "12",
      "LotType": "COE",
      "FarmName": "Fazenda Cachoeirinha",
      "ProducerName": "Amaury Junqueira Villela",
      "Region": "Carmo de Minas, Minas Gerais",
      "Process": "Pulped Natural",
      "Varietal": "",
      "WeightKg": null,
      "ScoreCoE": 87.07,
      "PriceUSDPerLb": 4.16,
      "TotalValueUSD": 11555.75,
      "BuyerName": "Ishimitsu for Kobe Coffee Co., Ltd.",
      "ScrapedMonth": "2026-06"
    },
    {
      "AuctionSlug": "brazil-pulped-naturals-2003",
      "AuctionYear": 2003,
      "Country": "Brazil",
      "LotRank": "13",
      "LotType": "COE",
      "FarmName": "S\u00edtio Vivenda das \u00c1guas",
      "ProducerName": "Ant\u00f4nio Ciro Santana",
      "Region": "Vi\u00e7osa, Minas Gerais",
      "Process": "Pulped Natural",
      "Varietal": "",
      "WeightKg": null,
      "ScoreCoE": 86.89,
      "PriceUSDPerLb": 2.14,
      "TotalValueUSD": 9907.57,
      "BuyerName": "VOLCAFE Specialty Coffee for the Tamarindo group: Ecco Caffe, Sweet Marias, Origins Coffee Roasters, Boot Coffee and Hunter Bay",
      "ScrapedMonth": "2026-06"
    },
    {
      "AuctionSlug": "brazil-pulped-naturals-2003",
      "AuctionYear": 2003,
      "Country": "Brazil",
      "LotRank": "14",
      "LotType": "COE",
      "FarmName": "Fazenda Santa Terezinha",
      "ProducerName": "Paulo S\u00e9rgio de Almeida",
      "Region": "Parais\u00f3polis, Minas Gerais",
      "Process": "Pulped Natural",
      "Varietal": "",
      "WeightKg": null,
      "ScoreCoE": 86.8,
      "PriceUSDPerLb": 2.65,
      "TotalValueUSD": 7361.23,
      "BuyerName": "Mercanta The Coffee Hunters for The Golden Coffee Box and San Francsico Coffee Malaysia",
      "ScrapedMonth": "2026-06"
    },
    {
      "AuctionSlug": "brazil-pulped-naturals-2003",
      "AuctionYear": 2003,
      "Country": "Brazil",
      "LotRank": "15",
      "LotType": "COE",
      "FarmName": "Fazenda C\u00f3rrego do Retiro",
      "ProducerName": "Railda Maria de Rezende Saraiva",
      "Region": "Arax\u00e1, Minas Gerais",
      "Process": "Pulped Natural",
      "Varietal": "",
      "WeightKg": null,
      "ScoreCoE": 86.8,
      "PriceUSDPerLb": 1.95,
      "TotalValueUSD": 6448.52,
      "BuyerName": "Mercanta The Coffee Hunters for Union Coffee Roasters",
      "ScrapedMonth": "2026-06"
    },
    {
      "AuctionSlug": "brazil-pulped-naturals-2003",
      "AuctionYear": 2003,
      "Country": "Brazil",
      "LotRank": "16",
      "LotType": "COE",
      "FarmName": "Fazenda Barreiro",
      "ProducerName": "Carlos Alberto Paiva Pellicer",
      "Region": "Monte Santo de Minas, Minas Gerais",
      "Process": "Pulped Natural",
      "Varietal": "",
      "WeightKg": null,
      "ScoreCoE": 86.67,
      "PriceUSDPerLb": 1.31,
      "TotalValueUSD": 14555.8,
      "BuyerName": "Arvid Nordquist H.A.B.",
      "ScrapedMonth": "2026-06"
    },
    {
      "AuctionSlug": "brazil-pulped-naturals-2003",
      "AuctionYear": 2003,
      "Country": "Brazil",
      "LotRank": "17",
      "LotType": "COE",
      "FarmName": "Fazenda do Ros\u00e1rio",
      "ProducerName": "Jos\u00e9 Ribeiro de Carvalho",
      "Region": "Dom Vi\u00e7oso, Minas Gerais",
      "Process": "Pulped Natural",
      "Varietal": "",
      "WeightKg": null,
      "ScoreCoE": 86.63,
      "PriceUSDPerLb": 1.51,
      "TotalValueUSD": 4394.25,
      "BuyerName": "Schlueter & Maack for Laier Kaffee, Saerve Kaffee, Rubens Kaffee.",
      "ScrapedMonth": "2026-06"
    },
    {
      "AuctionSlug": "brazil-pulped-naturals-2003",
      "AuctionYear": 2003,
      "Country": "Brazil",
      "LotRank": "18",
      "LotType": "COE",
      "FarmName": "Fazenda Cachoeira do Cambu\u00ed 2",
      "ProducerName": "Ad\u00f4nis Galileu dos Santos",
      "Region": "Muzambinho, Minas Gerais",
      "Process": "Pulped Natural",
      "Varietal": "",
      "WeightKg": null,
      "ScoreCoE": 86.43,
      "PriceUSDPerLb": 2.05,
      "TotalValueUSD": 6236.88,
      "BuyerName": "Schlueter & Maack for Hagen Kaffee",
      "ScrapedMonth": "2026-06"
    },
    {
      "AuctionSlug": "brazil-pulped-naturals-2003",
      "AuctionYear": 2003,
      "Country": "Brazil",
      "LotRank": "19",
      "LotType": "COE",
      "FarmName": "Brauna",
      "ProducerName": "Demerval Aguiar Macedo",
      "Region": "Araponga, Minas Gerais",
      "Process": "Pulped Natural",
      "Varietal": "",
      "WeightKg": null,
      "ScoreCoE": 86.3,
      "PriceUSDPerLb": 2.05,
      "TotalValueUSD": 5423.37,
      "BuyerName": "UNICAFE INC.",
      "ScrapedMonth": "2026-06"
    },
    {
      "AuctionSlug": "brazil-pulped-naturals-2003",
      "AuctionYear": 2003,
      "Country": "Brazil",
      "LotRank": "20",
      "LotType": "COE",
      "FarmName": "S\u00edtio Arauc\u00e1ria",
      "ProducerName": "Kleber de Castro Junqueira",
      "Region": "Carmo de Minas, MG",
      "Process": "Pulped Natural",
      "Varietal": "",
      "WeightKg": null,
      "ScoreCoE": 86.11,
      "PriceUSDPerLb": 2.06,
      "TotalValueUSD": 7084.78,
      "BuyerName": "VOLCAFE Specialty Coffee for the Tamarindo group: Ecco Caffe, Sweet Marias, Origins Coffee Roasterie, Boot Coffee and Hunter Bay",
      "ScrapedMonth": "2026-06"
    },
    {
      "AuctionSlug": "brazil-pulped-naturals-2003",
      "AuctionYear": 2003,
      "Country": "Brazil",
      "LotRank": "21",
      "LotType": "COE",
      "FarmName": "S\u00edtio Dos Estouros",
      "ProducerName": "Jos\u00e9 Mauro Miranda",
      "Region": "Carmo De Minas, Matas de Minas",
      "Process": "Pulped Natural",
      "Varietal": "",
      "WeightKg": null,
      "ScoreCoE": 86.09,
      "PriceUSDPerLb": 2.06,
      "TotalValueUSD": 8992.21,
      "BuyerName": "Caravan Coffee Co.,Ltd.",
      "ScrapedMonth": "2026-06"
    },
    {
      "AuctionSlug": "brazil-pulped-naturals-2003",
      "AuctionYear": 2003,
      "Country": "Brazil",
      "LotRank": "22",
      "LotType": "COE",
      "FarmName": "Fazenda Sert\u00e3o",
      "ProducerName": "Nazareth Dias Pereira",
      "Region": "Carmo de Minas, MG",
      "Process": "Pulped Natural",
      "Varietal": "",
      "WeightKg": null,
      "ScoreCoE": 86.04,
      "PriceUSDPerLb": 3.35,
      "TotalValueUSD": 18611.42,
      "BuyerName": "WATARU for KYOWA\u2019S COFFEE",
      "ScrapedMonth": "2026-06"
    },
    {
      "AuctionSlug": "brazil-pulped-naturals-2003",
      "AuctionYear": 2003,
      "Country": "Brazil",
      "LotRank": "23",
      "LotType": "COE",
      "FarmName": "S\u00edtio Bela Vista",
      "ProducerName": "M\u00e1rcio Heleno de Carvalho Junqueira",
      "Region": "Dom Vi\u00e7oso, MG",
      "Process": "Pulped Natural",
      "Varietal": "",
      "WeightKg": null,
      "ScoreCoE": 85.83,
      "PriceUSDPerLb": 2.15,
      "TotalValueUSD": 6256.72,
      "BuyerName": "TIME\u2019S CLUB INC.",
      "ScrapedMonth": "2026-06"
    },
    {
      "AuctionSlug": "brazil-pulped-naturals-2003",
      "AuctionYear": 2003,
      "Country": "Brazil",
      "LotRank": "24",
      "LotType": "COE",
      "FarmName": "Fazenda Embiral",
      "ProducerName": "Benedito Pereira Faria",
      "Region": "Pouso Alto, Minas Gerais",
      "Process": "Pulped Natural",
      "Varietal": "",
      "WeightKg": null,
      "ScoreCoE": 85.74,
      "PriceUSDPerLb": 4.15,
      "TotalValueUSD": 9881.12,
      "BuyerName": "World Coffee Co.,Ltd.",
      "ScrapedMonth": "2026-06"
    },
    {
      "AuctionSlug": "brazil-pulped-naturals-2003",
      "AuctionYear": 2003,
      "Country": "Brazil",
      "LotRank": "25",
      "LotType": "COE",
      "FarmName": "Fazenda Santana",
      "ProducerName": "Maria Aparecida Pereira",
      "Region": "Ol\u00edmpio Noronha, Minas Gerais",
      "Process": "Pulped Natural",
      "Varietal": "",
      "WeightKg": null,
      "ScoreCoE": 85.41,
      "PriceUSDPerLb": 3.16,
      "TotalValueUSD": 10449.91,
      "BuyerName": "Wataru & Co., Ltd.",
      "ScrapedMonth": "2026-06"
    },
    {
      "AuctionSlug": "brazil-pulped-naturals-2003",
      "AuctionYear": 2003,
      "Country": "Brazil",
      "LotRank": "26",
      "LotType": "COE",
      "FarmName": "S\u00edtio Vila Maria",
      "ProducerName": "Jos\u00e9 Ev\u00eancio Pola",
      "Region": "Vargem Alta, Esp\u00edrito Santo",
      "Process": "Pulped Natural",
      "Varietal": "",
      "WeightKg": null,
      "ScoreCoE": 85.28,
      "PriceUSDPerLb": 2.3,
      "TotalValueUSD": 6693.23,
      "BuyerName": "Wataru & Co., Ltd.",
      "ScrapedMonth": "2026-06"
    },
    {
      "AuctionSlug": "brazil-pulped-naturals-2003",
      "AuctionYear": 2003,
      "Country": "Brazil",
      "LotRank": "27",
      "LotType": "COE",
      "FarmName": "Fazenda Pedra Redonda",
      "ProducerName": "Jos\u00e9 Bernardes Santana",
      "Region": "Araponga, Minas Gerais",
      "Process": "Pulped Natural",
      "Varietal": "",
      "WeightKg": null,
      "ScoreCoE": 84.98,
      "PriceUSDPerLb": 2.01,
      "TotalValueUSD": 5317.55,
      "BuyerName": "Wataru & Co., Ltd.",
      "ScrapedMonth": "2026-06"
    },
    {
      "AuctionSlug": "brazil-pulped-naturals-2003",
      "AuctionYear": 2003,
      "Country": "Brazil",
      "LotRank": "28",
      "LotType": "COE",
      "FarmName": "Fazenda Laranja Cravo",
      "ProducerName": "Romeu F Junqueira Guimar\u00e3es e Outro",
      "Region": "Pouso Alto, Minas Gerais",
      "Process": "Pulped Natural",
      "Varietal": "",
      "WeightKg": null,
      "ScoreCoE": 84.98,
      "PriceUSDPerLb": 2.1,
      "TotalValueUSD": 7777.91,
      "BuyerName": "Sweet Maria\u2019s",
      "ScrapedMonth": "2026-06"
    },
    {
      "AuctionSlug": "brazil-pulped-naturals-2003",
      "AuctionYear": 2003,
      "Country": "Brazil",
      "LotRank": "29",
      "LotType": "COE",
      "FarmName": "S\u00edtio Tranquilidade",
      "ProducerName": "Jos\u00e9 Ant\u00f4nio Nicolau Ferreira",
      "Region": "Tejup\u00e1, S\u00e3o Paulo",
      "Process": "Pulped Natural",
      "Varietal": "",
      "WeightKg": null,
      "ScoreCoE": 84.76,
      "PriceUSDPerLb": 1.96,
      "TotalValueUSD": 11407.6,
      "BuyerName": "Bettys Cafe Tea Rooms",
      "ScrapedMonth": "2026-06"
    },
    {
      "AuctionSlug": "brazil-pulped-naturals-2003",
      "AuctionYear": 2003,
      "Country": "Brazil",
      "LotRank": "30",
      "LotType": "COE",
      "FarmName": "S\u00edtio Serrabr\u00e1z",
      "ProducerName": "Luiz Ant\u00f4nio Vergueiro",
      "Region": "Parais\u00f3polis, Minas Gerais",
      "Process": "Pulped Natural",
      "Varietal": "",
      "WeightKg": null,
      "ScoreCoE": 84.26,
      "PriceUSDPerLb": 1.7,
      "TotalValueUSD": 4947.17,
      "BuyerName": "Schlueter & Maack for Mondo del Caff\u00e8",
      "ScrapedMonth": "2026-06"
    },
    {
      "AuctionSlug": "brazil-pulped-naturals-2003",
      "AuctionYear": 2003,
      "Country": "Brazil",
      "LotRank": "31",
      "LotType": "COE",
      "FarmName": "Est\u00e2ncia Tijuco Preto",
      "ProducerName": "Jos\u00e9 F\u00e1varo",
      "Region": "Tejup\u00e1, S\u00e3o Paulo",
      "Process": "Pulped Natural",
      "Varietal": "",
      "WeightKg": null,
      "ScoreCoE": 84.04,
      "PriceUSDPerLb": 2.06,
      "TotalValueUSD": 5449.83,
      "BuyerName": "World Coffee Co.,Ltd.",
      "ScrapedMonth": "2026-06"
    },
    {
      "AuctionSlug": "brazil-pulped-naturals-2003",
      "AuctionYear": 2003,
      "Country": "Brazil",
      "LotRank": "32",
      "LotType": "COE",
      "FarmName": "Fazenda Tijuco Preto",
      "ProducerName": "Ant\u00f4nio M\u00e1rcio Pereira de Castro",
      "Region": "Carmo de Minas, Minas Gerais",
      "Process": "Pulped Natural",
      "Varietal": "",
      "WeightKg": null,
      "ScoreCoE": 84.0,
      "PriceUSDPerLb": 2.7,
      "TotalValueUSD": 6785.83,
      "BuyerName": "World Coffee Co.,Ltd.",
      "ScrapedMonth": "2026-06"
    },
    {
      "AuctionSlug": "brazil-pulped-naturals-2003",
      "AuctionYear": 2003,
      "Country": "Brazil",
      "LotRank": "33",
      "LotType": "COE",
      "FarmName": "Ch\u00e1cara Sagrado Cora\u00e7\u00e3o De\u2026",
      "ProducerName": "Alvaro Ant\u00f4nio Pereira Coli",
      "Region": "Carmo De Minas, Sul De Minas",
      "Process": "Pulped Natural",
      "Varietal": "",
      "WeightKg": null,
      "ScoreCoE": 83.83,
      "PriceUSDPerLb": 2.35,
      "TotalValueUSD": 7149.59,
      "BuyerName": "Wataru & Co., Ltd.",
      "ScrapedMonth": "2026-06"
    },
    {
      "AuctionSlug": "brazil-pulped-naturals-2003",
      "AuctionYear": 2003,
      "Country": "Brazil",
      "LotRank": "34",
      "LotType": "COE",
      "FarmName": "Fazenda S\u00e3o Gabriel",
      "ProducerName": "Isaac Ribeiro Gabriel",
      "Region": "Guaxup\u00e9, Minas Gerais",
      "Process": "Pulped Natural",
      "Varietal": "",
      "WeightKg": null,
      "ScoreCoE": 83.37,
      "PriceUSDPerLb": 3.3,
      "TotalValueUSD": 8293.79,
      "BuyerName": "Nippon Coffee Trading Co., Ltd.",
      "ScrapedMonth": "2026-06"
    },
    {
      "AuctionSlug": "brazil-pulped-naturals-2003",
      "AuctionYear": 2003,
      "Country": "Brazil",
      "LotRank": "35",
      "LotType": "COE",
      "FarmName": "S\u00edtio do Sert\u00e3ozinho",
      "ProducerName": "Jos\u00e9 Wagner Ribeiro",
      "Region": "Cristina, Minas Gerais",
      "Process": "Pulped Natural",
      "Varietal": "",
      "WeightKg": null,
      "ScoreCoE": 83.33,
      "PriceUSDPerLb": 5.1,
      "TotalValueUSD": 14166.9,
      "BuyerName": "Ishimitsu for Kobe Coffee Co., Ltd.",
      "ScrapedMonth": "2026-06"
    },
    {
      "AuctionSlug": "brazil-pulped-naturals-2003",
      "AuctionYear": 2003,
      "Country": "Brazil",
      "LotRank": "36",
      "LotType": "COE",
      "FarmName": "Fazenda Sto Ant\u00f4nio do\u2026",
      "ProducerName": "Renata Vargas Rigo de Souza",
      "Region": "Concei\u00e7\u00e3o do Castelo, Esp\u00edrito Santo",
      "Process": "Pulped Natural",
      "Varietal": "",
      "WeightKg": null,
      "ScoreCoE": 83.3,
      "PriceUSDPerLb": 1.35,
      "TotalValueUSD": 3571.49,
      "BuyerName": "Maruyama Coffee",
      "ScrapedMonth": "2026-06"
    },
    {
      "AuctionSlug": "brazil-pulped-naturals-2003",
      "AuctionYear": 2003,
      "Country": "Brazil",
      "LotRank": "37",
      "LotType": "COE",
      "FarmName": "Fazenda Campo de Ouro",
      "ProducerName": "Jos\u00e9 Ferreira Filho",
      "Region": "Piraj\u00fa, S\u00e3o Paulo",
      "Process": "Pulped Natural",
      "Varietal": "",
      "WeightKg": null,
      "ScoreCoE": 83.07,
      "PriceUSDPerLb": 2.05,
      "TotalValueUSD": 27116.86,
      "BuyerName": "Gloria Jean\u2019s Gourmet Coffee, Inc.",
      "ScrapedMonth": "2026-06"
    },
    {
      "AuctionSlug": "brazil-pulped-naturals-2003",
      "AuctionYear": 2003,
      "Country": "Brazil",
      "LotRank": "38",
      "LotType": "COE",
      "FarmName": "Fazenda S\u00e3o Marcos",
      "ProducerName": "Norival F\u00e1varo",
      "Region": "Sarutai\u00e1, S\u00e3o Paulo",
      "Process": "Pulped Natural",
      "Varietal": "",
      "WeightKg": null,
      "ScoreCoE": 82.63,
      "PriceUSDPerLb": 1.8,
      "TotalValueUSD": 6666.78,
      "BuyerName": "Timothy\u2019s World Coffee",
      "ScrapedMonth": "2026-06"
    },
    {
      "AuctionSlug": "brazil-pulped-naturals-2003",
      "AuctionYear": 2003,
      "Country": "Brazil",
      "LotRank": "39",
      "LotType": "COE",
      "FarmName": "Fazenda Irm\u00e3os Tomazini",
      "ProducerName": "Solimar Tomazini",
      "Region": "Castelo, Esp\u00edrito Santo",
      "Process": "Pulped Natural",
      "Varietal": "",
      "WeightKg": null,
      "ScoreCoE": 82.63,
      "PriceUSDPerLb": 2.05,
      "TotalValueUSD": 5694.54,
      "BuyerName": "UNICAFE INC.",
      "ScrapedMonth": "2026-06"
    },
    {
      "AuctionSlug": "brazil-pulped-naturals-2003",
      "AuctionYear": 2003,
      "Country": "Brazil",
      "LotRank": "40",
      "LotType": "COE",
      "FarmName": "Fazenda Bela Vista",
      "ProducerName": "Luiz Carlos Queiroz",
      "Region": "Mucuge, Bahia",
      "Process": "Pulped Natural",
      "Varietal": "",
      "WeightKg": null,
      "ScoreCoE": 82.11,
      "PriceUSDPerLb": 2.01,
      "TotalValueUSD": 15155.02,
      "BuyerName": "KATOCOFFEE Inc.",
      "ScrapedMonth": "2026-06"
    },
    {
      "AuctionSlug": "brazil-pulped-naturals-2003",
      "AuctionYear": 2003,
      "Country": "Brazil",
      "LotRank": "41",
      "LotType": "COE",
      "FarmName": "Fazenda Bra\u00fana",
      "ProducerName": "Afonso Jorge Schm\u00f6lz de Mattos",
      "Region": "Araponga, Minas Gerais",
      "Process": "Pulped Natural",
      "Varietal": "",
      "WeightKg": null,
      "ScoreCoE": 82.04,
      "PriceUSDPerLb": 2.5,
      "TotalValueUSD": 6613.87,
      "BuyerName": "Bewleys Ltd",
      "ScrapedMonth": "2026-06"
    },
    {
      "AuctionSlug": "brazil-pulped-naturals-2003",
      "AuctionYear": 2003,
      "Country": "Brazil",
      "LotRank": "42",
      "LotType": "COE",
      "FarmName": "S\u00edtio Primavera",
      "ProducerName": "F\u00e9lix Adalberto Nacif Santos",
      "Region": "Erv\u00e1lia, Minas Gerais",
      "Process": "Pulped Natural",
      "Varietal": "",
      "WeightKg": null,
      "ScoreCoE": 80.76,
      "PriceUSDPerLb": 1.31,
      "TotalValueUSD": 3292.38,
      "BuyerName": "MOKKA SPECIALITY COFFEE",
      "ScrapedMonth": "2026-06"
    },
    {
      "AuctionSlug": "brazil-pulped-naturals-2003",
      "AuctionYear": 2003,
      "Country": "Brazil",
      "LotRank": "43",
      "LotType": "COE",
      "FarmName": "Fazenda Coqueiros",
      "ProducerName": "Paulo S\u00e9rgio Carneiro Ribeiro e Outros",
      "Region": "Carmo de Minas, Minas Gerais",
      "Process": "Pulped Natural",
      "Varietal": "",
      "WeightKg": null,
      "ScoreCoE": 80.5,
      "PriceUSDPerLb": 1.9,
      "TotalValueUSD": 8042.46,
      "BuyerName": "S.ISHIMITSU & CO., LTD.",
      "ScrapedMonth": "2026-06"
    }
  ]
}