{
  "url": "https://allianceforcoffeeexcellence.org/colombia-south-2014/",
  "scraped_month": "2026-06",
  "lots": [
    {
      "AuctionSlug": "colombia-south-2014",
      "AuctionYear": 2014,
      "Country": "Colombia",
      "LotRank": "1",
      "LotType": "COE",
      "FarmName": "Bella Vista",
      "ProducerName": "Carmen Cecilia Montoya Pati\u00f1o",
      "Region": "Urrao, Antioquia",
      "Process": "",
      "Varietal": "",
      "WeightKg": null,
      "ScoreCoE": 91.31,
      "PriceUSDPerLb": 45.7,
      "TotalValueUSD": 117449.0,
      "BuyerName": "BANEXPORT S.A, Cafe 18, Cafe Palo Alto (Colombia) // Wataru & Co., Takamura Coffee Roasters (Japan) // Cafe Imports, George Howell Coffee, ZOKA Coffee (USA) // Cafe Libre, Hankook Coffee, 180 Roasters (S Korea) // HARU Cafe (Taiwan) // Union Hand Roasted Coffee (UK) // Single Origin Roasters (Australia)",
      "ScrapedMonth": "2026-06"
    },
    {
      "AuctionSlug": "colombia-south-2014",
      "AuctionYear": 2014,
      "Country": "Colombia",
      "LotRank": "2",
      "LotType": "COE",
      "FarmName": "El Cairo",
      "ProducerName": "Lucas German Melo Pinchao",
      "Region": "Consaca, Nari\u00f1o",
      "Process": "",
      "Varietal": "",
      "WeightKg": null,
      "ScoreCoE": 91.09,
      "PriceUSDPerLb": 22.2,
      "TotalValueUSD": 61649.4,
      "BuyerName": "Maruyama Coffee, Yamada Coffee, Yokoi Coffee, Iwai Coffee, Tabei Coffee, Coffee a Go Go, Cafe Maple, Ponpon Coffee, Uchida Coffee, Sugi Coffee Roasting, Branch Coffee, Thoth Coffee, Adachi Coffee, Saza Coffee",
      "ScrapedMonth": "2026-06"
    },
    {
      "AuctionSlug": "colombia-south-2014",
      "AuctionYear": 2014,
      "Country": "Colombia",
      "LotRank": "3",
      "LotType": "COE",
      "FarmName": "La Esperanza",
      "ProducerName": "Pablo Emilio Montoya Caro",
      "Region": "Urrao, Antioquia",
      "Process": "",
      "Varietal": "",
      "WeightKg": null,
      "ScoreCoE": 90.59,
      "PriceUSDPerLb": 22.2,
      "TotalValueUSD": 57054.0,
      "BuyerName": "Coffee Bean International, Specialty Coffee by Farmer Brothers",
      "ScrapedMonth": "2026-06"
    },
    {
      "AuctionSlug": "colombia-south-2014",
      "AuctionYear": 2014,
      "Country": "Colombia",
      "LotRank": "4",
      "LotType": "COE",
      "FarmName": "El Naranjo",
      "ProducerName": "Gonzalo Dagua Conda",
      "Region": "Caloto, Cauca",
      "Process": "",
      "Varietal": "",
      "WeightKg": null,
      "ScoreCoE": 89.31,
      "PriceUSDPerLb": 6.21,
      "TotalValueUSD": 22952.16,
      "BuyerName": "WATARU for TAKAMURA COFFEE ROASTERS, TAF COFFEE",
      "ScrapedMonth": "2026-06"
    },
    {
      "AuctionSlug": "colombia-south-2014",
      "AuctionYear": 2014,
      "Country": "Colombia",
      "LotRank": "5",
      "LotType": "COE",
      "FarmName": "Majagual",
      "ProducerName": "Jesus Maria Martinez Gomez",
      "Region": "Condordia , Antioquia",
      "Process": "",
      "Varietal": "",
      "WeightKg": null,
      "ScoreCoE": 89.13,
      "PriceUSDPerLb": 12.5,
      "TotalValueUSD": 34862.5,
      "BuyerName": "Terarosa Coffee",
      "ScrapedMonth": "2026-06"
    },
    {
      "AuctionSlug": "colombia-south-2014",
      "AuctionYear": 2014,
      "Country": "Colombia",
      "LotRank": "6",
      "LotType": "COE",
      "FarmName": "El Guamito",
      "ProducerName": "Bautista Dizu Dagua",
      "Region": "Jambalo, Cauca",
      "Process": "",
      "Varietal": "",
      "WeightKg": null,
      "ScoreCoE": 88.56,
      "PriceUSDPerLb": 10.35,
      "TotalValueUSD": 25833.6,
      "BuyerName": "ALMACIELO(S.KOREA), De Ballon(S.KOREA)",
      "ScrapedMonth": "2026-06"
    },
    {
      "AuctionSlug": "colombia-south-2014",
      "AuctionYear": 2014,
      "Country": "Colombia",
      "LotRank": "7",
      "LotType": "COE",
      "FarmName": "Las Palmas",
      "ProducerName": "Edgar Dagua Corpus",
      "Region": "Miranda, Cauca",
      "Process": "",
      "Varietal": "",
      "WeightKg": null,
      "ScoreCoE": 88.19,
      "PriceUSDPerLb": 9.1,
      "TotalValueUSD": 23159.5,
      "BuyerName": "HARU International Corp., M.I. COFFEE Co. LTD.",
      "ScrapedMonth": "2026-06"
    },
    {
      "AuctionSlug": "colombia-south-2014",
      "AuctionYear": 2014,
      "Country": "Colombia",
      "LotRank": "8",
      "LotType": "COE",
      "FarmName": "San Pedro",
      "ProducerName": "Olga Garzon de Diaz del Castillo",
      "Region": "Consaca, Nari\u00f1o",
      "Process": "",
      "Varietal": "",
      "WeightKg": null,
      "ScoreCoE": 87.91,
      "PriceUSDPerLb": 5.0,
      "TotalValueUSD": 23305.0,
      "BuyerName": "EL CAFE coffee roasters",
      "ScrapedMonth": "2026-06"
    },
    {
      "AuctionSlug": "colombia-south-2014",
      "AuctionYear": 2014,
      "Country": "Colombia",
      "LotRank": "9",
      "LotType": "COE",
      "FarmName": "Las Margaritas",
      "ProducerName": "Eduardo Torres Barreto",
      "Region": "Genova, Quindio",
      "Process": "",
      "Varietal": "",
      "WeightKg": null,
      "ScoreCoE": 87.69,
      "PriceUSDPerLb": 9.2,
      "TotalValueUSD": 22733.2,
      "BuyerName": "Time\u2019s Club, Coffee Libre, TASHIRO COFFEE Co., Ltd.",
      "ScrapedMonth": "2026-06"
    },
    {
      "AuctionSlug": "colombia-south-2014",
      "AuctionYear": 2014,
      "Country": "Colombia",
      "LotRank": "10",
      "LotType": "COE",
      "FarmName": "El Danubio",
      "ProducerName": "Oscar Sigifredo Trejos",
      "Region": "Toribio, Cauca",
      "Process": "",
      "Varietal": "",
      "WeightKg": null,
      "ScoreCoE": 87.5,
      "PriceUSDPerLb": 7.6,
      "TotalValueUSD": 18969.6,
      "BuyerName": "TOA COFFEE Co.,Ltd & ARAB COFFEE Co.,Ltd",
      "ScrapedMonth": "2026-06"
    },
    {
      "AuctionSlug": "colombia-south-2014",
      "AuctionYear": 2014,
      "Country": "Colombia",
      "LotRank": "11a",
      "LotType": "COE",
      "FarmName": "La Falda (2014)",
      "ProducerName": "Jose Arcadio Caro Rueda",
      "Region": "Urrao, Antioquia",
      "Process": "",
      "Varietal": "",
      "WeightKg": null,
      "ScoreCoE": 86.94,
      "PriceUSDPerLb": 8.5,
      "TotalValueUSD": 22159.5,
      "BuyerName": "Kyokuto Fadie Corporation",
      "ScrapedMonth": "2026-06"
    },
    {
      "AuctionSlug": "colombia-south-2014",
      "AuctionYear": 2014,
      "Country": "Colombia",
      "LotRank": "11b",
      "LotType": "COE",
      "FarmName": "El Aguacate",
      "ProducerName": "Jose Vincente Delgado Zarama",
      "Region": "Yacuanquer, Nari\u00f1o",
      "Process": "",
      "Varietal": "",
      "WeightKg": null,
      "ScoreCoE": 86.94,
      "PriceUSDPerLb": 7.2,
      "TotalValueUSD": 23623.2,
      "BuyerName": "Nippon Coffee Trading Co.,Ltd for Doi Coffee",
      "ScrapedMonth": "2026-06"
    },
    {
      "AuctionSlug": "colombia-south-2014",
      "AuctionYear": 2014,
      "Country": "Colombia",
      "LotRank": "12a",
      "LotType": "COE",
      "FarmName": "Verdum",
      "ProducerName": "Maria Elena Garces Posada",
      "Region": "Condordia, Antioquia",
      "Process": "",
      "Varietal": "",
      "WeightKg": null,
      "ScoreCoE": 86.84,
      "PriceUSDPerLb": 4.6,
      "TotalValueUSD": 14177.2,
      "BuyerName": "32cup, Cantata, DBC.nl, Vivasara, Caff\u00e9nation, lot61",
      "ScrapedMonth": "2026-06"
    },
    {
      "AuctionSlug": "colombia-south-2014",
      "AuctionYear": 2014,
      "Country": "Colombia",
      "LotRank": "12b",
      "LotType": "COE",
      "FarmName": "La Primavera",
      "ProducerName": "Salustriano Julicue Coicue",
      "Region": "Toribio, Cauca",
      "Process": "",
      "Varietal": "",
      "WeightKg": null,
      "ScoreCoE": 86.84,
      "PriceUSDPerLb": 7.65,
      "TotalValueUSD": 19002.6,
      "BuyerName": "Campos Coffee",
      "ScrapedMonth": "2026-06"
    },
    {
      "AuctionSlug": "colombia-south-2014",
      "AuctionYear": 2014,
      "Country": "Colombia",
      "LotRank": "13",
      "LotType": "COE",
      "FarmName": "La Loma",
      "ProducerName": "Ramon Arcelio Zapata Sepulveda",
      "Region": "Condordia, Antioquia",
      "Process": "",
      "Varietal": "",
      "WeightKg": null,
      "ScoreCoE": 86.83,
      "PriceUSDPerLb": 5.4,
      "TotalValueUSD": 13203.0,
      "BuyerName": "elbgold Roestkaffee GmbH",
      "ScrapedMonth": "2026-06"
    },
    {
      "AuctionSlug": "colombia-south-2014",
      "AuctionYear": 2014,
      "Country": "Colombia",
      "LotRank": "14",
      "LotType": "COE",
      "FarmName": "Las Colinas",
      "ProducerName": "Santiago Fernandez",
      "Region": "Caloto, Cauca",
      "Process": "",
      "Varietal": "",
      "WeightKg": null,
      "ScoreCoE": 86.78,
      "PriceUSDPerLb": 5.1,
      "TotalValueUSD": 14851.2,
      "BuyerName": "honuKATOCOFFEE Inc.",
      "ScrapedMonth": "2026-06"
    },
    {
      "AuctionSlug": "colombia-south-2014",
      "AuctionYear": 2014,
      "Country": "Colombia",
      "LotRank": "15",
      "LotType": "COE",
      "FarmName": "El Porvenir",
      "ProducerName": "Alba Janet Guacan Cebellos",
      "Region": "Yacuanquer, Nari\u00f1o",
      "Process": "",
      "Varietal": "",
      "WeightKg": null,
      "ScoreCoE": 86.63,
      "PriceUSDPerLb": 6.2,
      "TotalValueUSD": 15376.0,
      "BuyerName": "WATARU for OGAWA COFFEE",
      "ScrapedMonth": "2026-06"
    },
    {
      "AuctionSlug": "colombia-south-2014",
      "AuctionYear": 2014,
      "Country": "Colombia",
      "LotRank": "16",
      "LotType": "COE",
      "FarmName": "El Roble",
      "ProducerName": "Jairo Gomez Acosta",
      "Region": "Almaguer, Cauca",
      "Process": "",
      "Varietal": "",
      "WeightKg": null,
      "ScoreCoE": 86.45,
      "PriceUSDPerLb": 5.1,
      "TotalValueUSD": 12795.9,
      "BuyerName": "honuKATOCOFFEE Inc.",
      "ScrapedMonth": "2026-06"
    },
    {
      "AuctionSlug": "colombia-south-2014",
      "AuctionYear": 2014,
      "Country": "Colombia",
      "LotRank": "17",
      "LotType": "COE",
      "FarmName": "Agua Caliente",
      "ProducerName": "Emeterio Narvaez Oviedo",
      "Region": "El Tablon, Nari\u00f1o",
      "Process": "",
      "Varietal": "",
      "WeightKg": null,
      "ScoreCoE": 86.38,
      "PriceUSDPerLb": 5.1,
      "TotalValueUSD": 12729.6,
      "BuyerName": "Campos Coffee",
      "ScrapedMonth": "2026-06"
    },
    {
      "AuctionSlug": "colombia-south-2014",
      "AuctionYear": 2014,
      "Country": "Colombia",
      "LotRank": "18",
      "LotType": "COE",
      "FarmName": "El Fresno",
      "ProducerName": "Maria Helena Martinez de Rosero",
      "Region": "San Lorenzo, Nari\u00f1o",
      "Process": "",
      "Varietal": "",
      "WeightKg": null,
      "ScoreCoE": 86.28,
      "PriceUSDPerLb": 4.4,
      "TotalValueUSD": 11136.4,
      "BuyerName": "MC FOODS LIMITED",
      "ScrapedMonth": "2026-06"
    },
    {
      "AuctionSlug": "colombia-south-2014",
      "AuctionYear": 2014,
      "Country": "Colombia",
      "LotRank": "19a",
      "LotType": "COE",
      "FarmName": "Tamboral",
      "ProducerName": "Marleny Guarin Ocampo",
      "Region": "Aguadas, Caldas",
      "Process": "",
      "Varietal": "",
      "WeightKg": null,
      "ScoreCoE": 86.25,
      "PriceUSDPerLb": 4.2,
      "TotalValueUSD": 10432.8,
      "BuyerName": "GSC International Co., Ltd. (KOREA) // Shanghai Borong International Trading Co., Ltd (CHINA)",
      "ScrapedMonth": "2026-06"
    },
    {
      "AuctionSlug": "colombia-south-2014",
      "AuctionYear": 2014,
      "Country": "Colombia",
      "LotRank": "19b",
      "LotType": "COE",
      "FarmName": "El Balso",
      "ProducerName": "Libardo Lasso Mu\u00f1oz",
      "Region": "Buesaco, Nari\u00f1o",
      "Process": "",
      "Varietal": "",
      "WeightKg": null,
      "ScoreCoE": 86.25,
      "PriceUSDPerLb": 4.2,
      "TotalValueUSD": 10537.8,
      "BuyerName": "Wataru & Co., Ltd",
      "ScrapedMonth": "2026-06"
    },
    {
      "AuctionSlug": "colombia-south-2014",
      "AuctionYear": 2014,
      "Country": "Colombia",
      "LotRank": "20",
      "LotType": "COE",
      "FarmName": "El Naranjal",
      "ProducerName": "Carlos Julio Diaz Pe\u00f1aloza",
      "Region": "Ibague, Tolima",
      "Process": "",
      "Varietal": "",
      "WeightKg": null,
      "ScoreCoE": 86.13,
      "PriceUSDPerLb": 5.25,
      "TotalValueUSD": 13928.25,
      "BuyerName": "InterAmerican Coffee GmbH",
      "ScrapedMonth": "2026-06"
    },
    {
      "AuctionSlug": "colombia-south-2014",
      "AuctionYear": 2014,
      "Country": "Colombia",
      "LotRank": "21",
      "LotType": "COE",
      "FarmName": "El Cucho",
      "ProducerName": "Emilio Bastidas Yela",
      "Region": "Samaniego, Nari\u00f1o",
      "Process": "",
      "Varietal": "",
      "WeightKg": null,
      "ScoreCoE": 86.03,
      "PriceUSDPerLb": 4.4,
      "TotalValueUSD": 11026.4,
      "BuyerName": "32cup, Cantata, DBC.nl, Vivasara, Caff\u00e9nation",
      "ScrapedMonth": "2026-06"
    },
    {
      "AuctionSlug": "colombia-south-2014",
      "AuctionYear": 2014,
      "Country": "Colombia",
      "LotRank": "22",
      "LotType": "COE",
      "FarmName": "El Naranjo",
      "ProducerName": "Omar Henry Cuaji Guevara",
      "Region": "Sotara, Cauca",
      "Process": "",
      "Varietal": "",
      "WeightKg": null,
      "ScoreCoE": 85.97,
      "PriceUSDPerLb": 4.1,
      "TotalValueUSD": 13899.0,
      "BuyerName": "GSC International Co., Ltd. (KOREA) // Shanghai Borong International Trading Co., Ltd (CHINA)",
      "ScrapedMonth": "2026-06"
    },
    {
      "AuctionSlug": "colombia-south-2014",
      "AuctionYear": 2014,
      "Country": "Colombia",
      "LotRank": "23a",
      "LotType": "COE",
      "FarmName": "Cortina de Hierro",
      "ProducerName": "Leonid Ramirez Conde",
      "Region": "Genova, Quindio",
      "Process": "",
      "Varietal": "",
      "WeightKg": null,
      "ScoreCoE": 85.84,
      "PriceUSDPerLb": 4.2,
      "TotalValueUSD": 11466.0,
      "BuyerName": "Wataru & Co., Ltd",
      "ScrapedMonth": "2026-06"
    },
    {
      "AuctionSlug": "colombia-south-2014",
      "AuctionYear": 2014,
      "Country": "Colombia",
      "LotRank": "23b",
      "LotType": "COE",
      "FarmName": "Hueco Lindo",
      "ProducerName": "Jaime Bolanos Lasso",
      "Region": "San Lorenzo, Nari\u00f1o",
      "Process": "",
      "Varietal": "",
      "WeightKg": null,
      "ScoreCoE": 85.84,
      "PriceUSDPerLb": 4.2,
      "TotalValueUSD": 10537.8,
      "BuyerName": "Cafe DAZAC, Coffee Sallim Factory, Juk-dong Cafe D, NIRVANA Coffee, Beanstore(Buchon), Crema Costa",
      "ScrapedMonth": "2026-06"
    },
    {
      "AuctionSlug": "colombia-south-2014",
      "AuctionYear": 2014,
      "Country": "Colombia",
      "LotRank": "24",
      "LotType": "COE",
      "FarmName": "Limoncito",
      "ProducerName": "Jaime Narvaez Ibarra",
      "Region": "El Tablon, Nari\u00f1o",
      "Process": "",
      "Varietal": "",
      "WeightKg": null,
      "ScoreCoE": 85.78,
      "PriceUSDPerLb": 4.9,
      "TotalValueUSD": 12107.9,
      "BuyerName": "Kaffebrenneriet as",
      "ScrapedMonth": "2026-06"
    },
    {
      "AuctionSlug": "colombia-south-2014",
      "AuctionYear": 2014,
      "Country": "Colombia",
      "LotRank": "25a",
      "LotType": "COE",
      "FarmName": "La Hermosa",
      "ProducerName": "Karen Jackeline Montero",
      "Region": "Santander, Cauca",
      "Process": "",
      "Varietal": "",
      "WeightKg": null,
      "ScoreCoE": 85.75,
      "PriceUSDPerLb": 5.75,
      "TotalValueUSD": 14990.25,
      "BuyerName": "Single Origin Roasters, ONA Coffee",
      "ScrapedMonth": "2026-06"
    },
    {
      "AuctionSlug": "colombia-south-2014",
      "AuctionYear": 2014,
      "Country": "Colombia",
      "LotRank": "25b",
      "LotType": "COE",
      "FarmName": "Los Curos",
      "ProducerName": "Purificacion Ortiz Ortiz",
      "Region": "Bucarasica, Norte de Santander",
      "Process": "",
      "Varietal": "",
      "WeightKg": null,
      "ScoreCoE": 85.75,
      "PriceUSDPerLb": 4.2,
      "TotalValueUSD": 10470.6,
      "BuyerName": "RYANS COFFEE ROASTERS, S. W. Park, DILI KAPO COFFEE ROASTERS, CORNER HILL, KOALA COFFEE FACTORY, Cafe Si-Gom, Sim\u2019s Coffee, Cafe Nara, Cafe Hong-si, Cafe Mule, Retro60 Coffee",
      "ScrapedMonth": "2026-06"
    },
    {
      "AuctionSlug": "colombia-south-2014",
      "AuctionYear": 2014,
      "Country": "Colombia",
      "LotRank": "26a",
      "LotType": "COE",
      "FarmName": "San Sabastian",
      "ProducerName": "Jaime Andres Romero Melo",
      "Region": "Samaniego, Nari\u00f1o",
      "Process": "",
      "Varietal": "",
      "WeightKg": null,
      "ScoreCoE": 85.63,
      "PriceUSDPerLb": 4.0,
      "TotalValueUSD": 10004.0,
      "BuyerName": "Wataru & Co., Ltd",
      "ScrapedMonth": "2026-06"
    },
    {
      "AuctionSlug": "colombia-south-2014",
      "AuctionYear": 2014,
      "Country": "Colombia",
      "LotRank": "26b",
      "LotType": "COE",
      "FarmName": "Marmato",
      "ProducerName": "Medardo Tuquerres Gomez",
      "Region": "Almaguer, Cauca",
      "Process": "",
      "Varietal": "",
      "WeightKg": null,
      "ScoreCoE": 85.63,
      "PriceUSDPerLb": 4.2,
      "TotalValueUSD": 10483.2,
      "BuyerName": "Bohemian(Anam-dong), Brilliant Coffee Roasters",
      "ScrapedMonth": "2026-06"
    },
    {
      "AuctionSlug": "colombia-south-2014",
      "AuctionYear": 2014,
      "Country": "Colombia",
      "LotRank": "27",
      "LotType": "COE",
      "FarmName": "Villa Maria",
      "ProducerName": "Jose Rodrigo Pantoja Arteaga",
      "Region": "Samaniego, Nari\u00f1o",
      "Process": "",
      "Varietal": "",
      "WeightKg": null,
      "ScoreCoE": 85.41,
      "PriceUSDPerLb": 4.25,
      "TotalValueUSD": 10684.5,
      "BuyerName": "Nippon Coffee Trading Co.,Ltd",
      "ScrapedMonth": "2026-06"
    },
    {
      "AuctionSlug": "colombia-south-2014",
      "AuctionYear": 2014,
      "Country": "Colombia",
      "LotRank": "28",
      "LotType": "COE",
      "FarmName": "El Jardin",
      "ProducerName": "John Fernando Hernandez Barrero",
      "Region": "Suaza, Hulia",
      "Process": "",
      "Varietal": "",
      "WeightKg": null,
      "ScoreCoE": 85.03,
      "PriceUSDPerLb": 4.0,
      "TotalValueUSD": 10000.0,
      "BuyerName": "Cafe DAZAC, Coffee Sallim Factory, Juk-dong Cafe D, NIRVANA Coffee, Beanstore(Buchon), Crema Costa",
      "ScrapedMonth": "2026-06"
    }
  ]
}