{
  "url": "https://allianceforcoffeeexcellence.org/guatemala-2007/",
  "scraped_month": "2026-06",
  "lots": [
    {
      "AuctionSlug": "guatemala-2007",
      "AuctionYear": 2007,
      "Country": "Guatemala",
      "LotRank": "1",
      "LotType": "COE",
      "FarmName": "El Socorro Y Anexos",
      "ProducerName": "Cercol, S. A. / Juan Diego de la Cerda",
      "Region": "Palencia, Guatemala",
      "Process": "",
      "Varietal": "",
      "WeightKg": null,
      "ScoreCoE": 93.6,
      "PriceUSDPerLb": 19.5,
      "TotalValueUSD": 44494.8,
      "BuyerName": "Solberg & Hansen AS",
      "ScrapedMonth": "2026-06"
    },
    {
      "AuctionSlug": "guatemala-2007",
      "AuctionYear": 2007,
      "Country": "Guatemala",
      "LotRank": "2",
      "LotType": "COE",
      "FarmName": "San Jose Oca\u00f1a",
      "ProducerName": "Carlos Roberto Sanchez Lazo Y Cd\u00f1os.",
      "Region": "San Juan Sacatep\u00e9quez, Guatemala",
      "Process": "",
      "Varietal": "",
      "WeightKg": null,
      "ScoreCoE": 91.5,
      "PriceUSDPerLb": 7.55,
      "TotalValueUSD": 45939.93,
      "BuyerName": "Caf\u00e9 Imports, 49th Parallel, Barefoot Coffee Roasters, Caffe Pronto, Coffee Klatch Roasting, Coffee Tree Roasters, Green Coffee Cooperative, Java Blend, Montana Coffee Traders, Paradise Roasters, PTs Coffee",
      "ScrapedMonth": "2026-06"
    },
    {
      "AuctionSlug": "guatemala-2007",
      "AuctionYear": 2007,
      "Country": "Guatemala",
      "LotRank": "3",
      "LotType": "COE",
      "FarmName": "San Jose El Yalu",
      "ProducerName": "Agropecuaria Los Pinos, S. A.",
      "Region": "Sumpango, Sacatepequez",
      "Process": "",
      "Varietal": "",
      "WeightKg": null,
      "ScoreCoE": 89.6,
      "PriceUSDPerLb": 9.15,
      "TotalValueUSD": 22270.22,
      "BuyerName": "Ritual Coffee Roasters, LLC",
      "ScrapedMonth": "2026-06"
    },
    {
      "AuctionSlug": "guatemala-2007",
      "AuctionYear": 2007,
      "Country": "Guatemala",
      "LotRank": "4",
      "LotType": "COE",
      "FarmName": "Asoc. De Caf. De San\u2026",
      "ProducerName": "Actasa",
      "Region": "San Cristobal Verapaz, Alta Verapaz",
      "Process": "",
      "Varietal": "",
      "WeightKg": null,
      "ScoreCoE": 89.53,
      "PriceUSDPerLb": 12.1,
      "TotalValueUSD": 27609.59,
      "BuyerName": "Maruyama Coffee for Mikatajuku group, Honey Coffee, Orsir Coffee",
      "ScrapedMonth": "2026-06"
    },
    {
      "AuctionSlug": "guatemala-2007",
      "AuctionYear": 2007,
      "Country": "Guatemala",
      "LotRank": "5",
      "LotType": "COE",
      "FarmName": "Santa Elisa Pachup",
      "ProducerName": "Proyectos Del Pacifico, S. A.",
      "Region": "Yepocapa, Chimaltenango",
      "Process": "",
      "Varietal": "",
      "WeightKg": null,
      "ScoreCoE": 88.48,
      "PriceUSDPerLb": 6.45,
      "TotalValueUSD": 18642.18,
      "BuyerName": "Toa Coffee Co.,Ltd.",
      "ScrapedMonth": "2026-06"
    },
    {
      "AuctionSlug": "guatemala-2007",
      "AuctionYear": 2007,
      "Country": "Guatemala",
      "LotRank": "6",
      "LotType": "COE",
      "FarmName": "El Injerto I",
      "ProducerName": "El Injerto, S. A.",
      "Region": "La Libertad, Huehuetenango",
      "Process": "",
      "Varietal": "",
      "WeightKg": null,
      "ScoreCoE": 88.28,
      "PriceUSDPerLb": 15.15,
      "TotalValueUSD": 36873.64,
      "BuyerName": "Stumptown Coffee Roasters",
      "ScrapedMonth": "2026-06"
    },
    {
      "AuctionSlug": "guatemala-2007",
      "AuctionYear": 2007,
      "Country": "Guatemala",
      "LotRank": "7",
      "LotType": "COE",
      "FarmName": "Teanzul",
      "ProducerName": "Compa\u00f1ia Agricola Tierra Alta, S. A.",
      "Region": "Barberena, Santa Rosa",
      "Process": "",
      "Varietal": "",
      "WeightKg": null,
      "ScoreCoE": 87.75,
      "PriceUSDPerLb": 6.05,
      "TotalValueUSD": 26689.27,
      "BuyerName": "Nippon Coffee Trading for Doi Coffee",
      "ScrapedMonth": "2026-06"
    },
    {
      "AuctionSlug": "guatemala-2007",
      "AuctionYear": 2007,
      "Country": "Guatemala",
      "LotRank": "8",
      "LotType": "COE",
      "FarmName": "Vista Hermosa",
      "ProducerName": "Martinez Pineda, Edwin",
      "Region": "San Pedro Necta, Huehuetenango",
      "Process": "",
      "Varietal": "",
      "WeightKg": null,
      "ScoreCoE": 87.53,
      "PriceUSDPerLb": 8.05,
      "TotalValueUSD": 19592.92,
      "BuyerName": "Kyokuto Fadie Corporation (Japan), Time\u2019s Club for C-COOP (Japan)",
      "ScrapedMonth": "2026-06"
    },
    {
      "AuctionSlug": "guatemala-2007",
      "AuctionYear": 2007,
      "Country": "Guatemala",
      "LotRank": "9",
      "LotType": "COE",
      "FarmName": "San Rafael Pacun",
      "ProducerName": "Cafetalera Catalu\u00f1a, S. A.",
      "Region": "Acatenango, Chimaltenango",
      "Process": "",
      "Varietal": "",
      "WeightKg": null,
      "ScoreCoE": 87.45,
      "PriceUSDPerLb": 7.0,
      "TotalValueUSD": 25555.99,
      "BuyerName": "Wataru & Co., Ltd.",
      "ScrapedMonth": "2026-06"
    },
    {
      "AuctionSlug": "guatemala-2007",
      "AuctionYear": 2007,
      "Country": "Guatemala",
      "LotRank": "10",
      "LotType": "COE",
      "FarmName": "Santa Ana Y Anexos",
      "ProducerName": "Servicios Polasek Alzamora Diaz M. S A",
      "Region": "Pueblo Nuevo Vi\u00f1as, Santa Rosa",
      "Process": "",
      "Varietal": "",
      "WeightKg": null,
      "ScoreCoE": 86.15,
      "PriceUSDPerLb": 5.47,
      "TotalValueUSD": 20802.27,
      "BuyerName": "Wataru & Co., Ltd.",
      "ScrapedMonth": "2026-06"
    },
    {
      "AuctionSlug": "guatemala-2007",
      "AuctionYear": 2007,
      "Country": "Guatemala",
      "LotRank": "11",
      "LotType": "COE",
      "FarmName": "El Porvenir",
      "ProducerName": "Soto Figueroa, Irma",
      "Region": "Amatitl\u00e1n, Guatemala",
      "Process": "",
      "Varietal": "",
      "WeightKg": null,
      "ScoreCoE": 85.95,
      "PriceUSDPerLb": 7.1,
      "TotalValueUSD": 20520.85,
      "BuyerName": "Royal Coffee New York, Nantucket Island Coffee Roasters, David\u2019s Beans/Rojo\u2019s Roastery, Coffee Labs, Phoenix Coffee, Coffee Depot, Portland Brew",
      "ScrapedMonth": "2026-06"
    },
    {
      "AuctionSlug": "guatemala-2007",
      "AuctionYear": 2007,
      "Country": "Guatemala",
      "LotRank": "12",
      "LotType": "COE",
      "FarmName": "Viviano",
      "ProducerName": "Gutierrez Vasquez, Bibiano",
      "Region": "Jalapa, Jalapa",
      "Process": "",
      "Varietal": "",
      "WeightKg": null,
      "ScoreCoE": 85.25,
      "PriceUSDPerLb": 6.3,
      "TotalValueUSD": 20125.34,
      "BuyerName": "Wataru for Toho",
      "ScrapedMonth": "2026-06"
    },
    {
      "AuctionSlug": "guatemala-2007",
      "AuctionYear": 2007,
      "Country": "Guatemala",
      "LotRank": "13",
      "LotType": "COE",
      "FarmName": "Daniel",
      "ProducerName": "Morales Alvarado, Daniel",
      "Region": "Mataquescuintla, Jalapa",
      "Process": "",
      "Varietal": "",
      "WeightKg": null,
      "ScoreCoE": 85.03,
      "PriceUSDPerLb": 6.3,
      "TotalValueUSD": 22042.04,
      "BuyerName": "Wataru & Co., Ltd.",
      "ScrapedMonth": "2026-06"
    },
    {
      "AuctionSlug": "guatemala-2007",
      "AuctionYear": 2007,
      "Country": "Guatemala",
      "LotRank": "14",
      "LotType": "COE",
      "FarmName": "El Platanar Y Anexos",
      "ProducerName": "De La Roca Perez, Hector",
      "Region": "Acatenango, Chimaltenango",
      "Process": "",
      "Varietal": "",
      "WeightKg": null,
      "ScoreCoE": 85.0,
      "PriceUSDPerLb": 6.45,
      "TotalValueUSD": 15698.68,
      "BuyerName": "Mercanta The Coffee Hunters for Fortnum and Mason London, Black Cat (Norway), Mokkamestarit (Finland), Rocket Coffee (New Zealand) and Kaffitar (Iceland).",
      "ScrapedMonth": "2026-06"
    },
    {
      "AuctionSlug": "guatemala-2007",
      "AuctionYear": 2007,
      "Country": "Guatemala",
      "LotRank": "15",
      "LotType": "COE",
      "FarmName": "Dos Marias",
      "ProducerName": "Finca Dos Marias, S. A.",
      "Region": "La Reforma, San Marcos",
      "Process": "",
      "Varietal": "",
      "WeightKg": null,
      "ScoreCoE": 84.88,
      "PriceUSDPerLb": 6.55,
      "TotalValueUSD": 15942.07,
      "BuyerName": "Green Mountain Coffee Roasters",
      "ScrapedMonth": "2026-06"
    },
    {
      "AuctionSlug": "guatemala-2007",
      "AuctionYear": 2007,
      "Country": "Guatemala",
      "LotRank": "16",
      "LotType": "COE",
      "FarmName": "Idolia",
      "ProducerName": "Diaz Marroquin, Roberto",
      "Region": "Pueblo Nuevo Vi\u00f1as, Santa Rosa",
      "Process": "",
      "Varietal": "",
      "WeightKg": null,
      "ScoreCoE": 84.75,
      "PriceUSDPerLb": 6.42,
      "TotalValueUSD": 17578.87,
      "BuyerName": "Cafe Leon, S.A.",
      "ScrapedMonth": "2026-06"
    },
    {
      "AuctionSlug": "guatemala-2007",
      "AuctionYear": 2007,
      "Country": "Guatemala",
      "LotRank": "17",
      "LotType": "COE",
      "FarmName": "Candelaria",
      "ProducerName": "Soto Figueroa, Irma",
      "Region": "Amatitl\u00e1n, Guatemala",
      "Process": "",
      "Varietal": "",
      "WeightKg": null,
      "ScoreCoE": 84.65,
      "PriceUSDPerLb": 5.5,
      "TotalValueUSD": 23426.32,
      "BuyerName": "World Coffee Co.,Ltd.",
      "ScrapedMonth": "2026-06"
    },
    {
      "AuctionSlug": "guatemala-2007",
      "AuctionYear": 2007,
      "Country": "Guatemala",
      "LotRank": "18",
      "LotType": "COE",
      "FarmName": "La Merced",
      "ProducerName": "Finca La Merced, S. A.",
      "Region": "San Mart\u00edn Jilotepeque, Chimaltenango",
      "Process": "",
      "Varietal": "",
      "WeightKg": null,
      "ScoreCoE": 84.25,
      "PriceUSDPerLb": 6.6,
      "TotalValueUSD": 22087.67,
      "BuyerName": "Kaffebrenneriet as",
      "ScrapedMonth": "2026-06"
    },
    {
      "AuctionSlug": "guatemala-2007",
      "AuctionYear": 2007,
      "Country": "Guatemala",
      "LotRank": "19",
      "LotType": "COE",
      "FarmName": "San Sebastian",
      "ProducerName": "Agropecuaria Salfar, S. A.",
      "Region": "San Miguel Due\u00f1as, Sacatepequez",
      "Process": "",
      "Varietal": "",
      "WeightKg": null,
      "ScoreCoE": 84.25,
      "PriceUSDPerLb": 6.5,
      "TotalValueUSD": 15820.37,
      "BuyerName": "El Cafetalito",
      "ScrapedMonth": "2026-06"
    }
  ]
}